tiktokenize/__init__.py
tiktokenize/tokenize.py
tiktokenize-0.0.1.dist-info/METADATA
tiktokenize-0.0.1.dist-info/WHEEL
tiktokenize-0.0.1.dist-info/entry_points.txt
tiktokenize-0.0.1.dist-info/RECORD
